typesense/__init__.py
typesense/alias.py
typesense/aliases.py
typesense/analytics.py
typesense/analytics_rule.py
typesense/analytics_rules.py
typesense/api_call.py
typesense/client.py
typesense/collection.py
typesense/collections.py
typesense/configuration.py
typesense/debug.py
typesense/document.py
typesense/documents.py
typesense/exceptions.py
typesense/key.py
typesense/keys.py
typesense/logger.py
typesense/multi_search.py
typesense/operations.py
typesense/override.py
typesense/overrides.py
typesense/preprocess.py
typesense/synonym.py
typesense/synonyms.py
typesense/validation.py
typesense_alt-0.17.1.dist-info/LICENSE
typesense_alt-0.17.1.dist-info/METADATA
typesense_alt-0.17.1.dist-info/WHEEL
typesense_alt-0.17.1.dist-info/top_level.txt
typesense_alt-0.17.1.dist-info/RECORD
