Metadata-Version: 2.1
Name: typesense-alt
Version: 0.17.1
Summary: Python client for Typesense, an open source and typo tolerant search engine.
Author-email: Typesense <contact@typesense.org>
License: Apache 2.0
Project-URL: Documentation, https://typesense.org/
Project-URL: Source, https://github.com/typesense/typesense-python
Project-URL: Tracker, https://github.com/typesense/typesense-python/issues
Keywords: search,typesense
Classifier: Development Status :: 5 - Production/Stable
Classifier: Intended Audience :: Developers
Classifier: License :: OSI Approved :: Apache Software License
Classifier: Programming Language :: Python
Classifier: Programming Language :: Python :: 3
Requires-Python: >=3
License-File: LICENSE
Requires-Dist: requests
